{
	"commentStamp" : "",
	"super" : "Object",
	"category" : "Cormas-Core-Tools",
	"classinstvars" : [
		"newFolder"
	],
	"pools" : [ ],
	"classvars" : [ ],
	"instvars" : [
		"fixedRandomSeed",
		"cormasModel",
		"simNumero",
		"randomSeed",
		"simName",
		"enableBackward",
		"dontAsk",
		"simFolder",
		"nextStep",
		"buttonsForwardAreOn",
		"deviationChoice",
		"listControle",
		"releaseRandomSeed",
		"listProbes",
		"fixRandomSeed",
		"listInit",
		"finalStep",
		"enableBackwardValue",
		"traceSize",
		"processRun",
		"processReplayBackward",
		"processReplayForward",
		"undoList",
		"redoList"
	],
	"name" : "CMSimManager",
	"type" : "normal"
}