{
	"class" : {
		"bosExtension" : " 31/3/15 09:57",
		"changeStepInterface" : " 31/3/15 09:57",
		"deviation2image" : " 31/3/15 09:57",
		"deviationImage" : " 31/3/15 09:57",
		"flecheImage" : " 31/3/15 09:57",
		"newFolder" : " 31/3/15 09:57",
		"newFolder:" : " 31/3/15 09:57",
		"newFolderName" : " 31/3/15 09:57",
		"scenarioBuilderInterface" : " 31/3/15 09:57",
		"separator" : " 31/3/15 09:57",
		"windowNewDeviation" : " 31/3/15 09:57" },
	"instance" : {
		"accept" : " 31/3/15 09:57",
		"allReplayButtonsTo:" : " 31/3/15 09:57",
		"applyUserChangeForFinalStep:" : " 31/3/15 09:57",
		"applyUserChangeForStep:" : " 31/3/15 09:57",
		"buttonsForwardAreOn" : " 31/3/15 09:57",
		"cancel" : " 31/3/15 09:57",
		"changedRandomSeed" : " 31/3/15 09:57",
		"confirmDeviation" : " 31/3/15 09:57",
		"copyPreviousBackStepsInNewFolder" : " 31/3/15 09:57",
		"cormas" : " 31/3/15 09:57",
		"cormasModel" : " 31/3/15 09:57",
		"cormasModel:" : " 31/3/15 09:57",
		"cormasModelClass" : " 31/3/15 09:57",
		"currentSimEnded" : " 31/3/15 09:57",
		"currentTime" : " 31/3/15 09:57",
		"currentTime:" : " 31/3/15 09:57",
		"deviationChoice" : " 31/3/15 09:57",
		"displayRunDuration:" : " 31/3/15 09:57",
		"dontAsk" : " 31/3/15 09:57",
		"enableBackward" : " 31/3/15 09:57",
		"enableBackward:" : " 31/3/15 09:57",
		"enableBackwardValue" : " 31/3/15 09:57",
		"finalStep" : " 31/3/15 09:57",
		"finalTime" : " 31/3/15 09:57",
		"finishSimulation" : " 31/3/15 09:57",
		"fixRandomSeed" : " 31/3/15 09:57",
		"fixedRandomSeed" : " 31/3/15 09:57",
		"fixedRandomSeed:" : " 31/3/15 09:57",
		"getStepNumberOfBosFilename:" : " 31/3/15 09:57",
		"initRandomSeed" : " 31/3/15 09:57",
		"initScenario" : " 31/3/15 09:57",
		"initScenarioWindow" : " 31/3/15 09:57",
		"initializeSimulation" : " 31/3/15 09:57",
		"intoASimulation" : " 31/3/15 09:57",
		"keepOrReleaseRandomSeed" : " 31/3/15 09:57",
		"listControle" : " 31/3/15 09:57",
		"listInit" : " 31/3/15 09:57",
		"listProbes" : " 31/3/15 09:57",
		"newSimName" : " 31/3/15 09:57",
		"nextStep" : " 31/3/15 09:57",
		"openNewDeviationWin" : " 31/3/15 09:57",
		"openReplayWin" : " 31/3/15 09:57",
		"openScenarioBuilderWin" : " 31/3/15 09:57",
		"randomSeed" : " 31/3/15 09:57",
		"randomSeed:" : " 31/3/15 09:57",
		"redo" : " 31/3/15 09:57",
		"redoList" : " 31/3/15 09:57",
		"redoList:" : " 31/3/15 09:57",
		"releaseRandomSeed" : " 31/3/15 09:57",
		"replayRunForward" : " 31/3/15 09:57",
		"replayStepForward" : " 31/3/15 09:57",
		"replayStepForward:" : " 31/3/15 09:57",
		"restoreOrganizationAt:" : " 31/3/15 09:57",
		"runBack" : " 31/3/15 09:57",
		"runSimulation" : " 31/3/15 09:57",
		"runSimulationThreaded" : " 31/3/15 09:57",
		"runSimulation_Basic" : " 31/3/15 09:57",
		"runStepByStep" : " 31/3/15 09:57",
		"setActiveProbes" : " 31/3/15 09:57",
		"setButtonsForTime0" : " 31/3/15 09:57",
		"setButtonsForTime1" : " 31/3/15 09:57",
		"setSimName" : " 31/3/15 09:57",
		"setStepMethod" : " 31/3/15 09:57",
		"simButtonAt:displayActivated:" : " 31/3/15 09:57",
		"simFolder" : " 31/3/15 09:57",
		"simFolder:" : " 31/3/15 09:57",
		"simName" : " 31/3/15 09:57",
		"simName:" : " 31/3/15 09:57",
		"simNameStart" : " 31/3/15 09:57",
		"simNumero" : " 31/3/15 09:57",
		"simNumero:" : " 31/3/15 09:57",
		"simRunButton_Pause:" : " 31/3/15 09:57",
		"snapshotCurrentState" : " 31/3/15 09:57",
		"stepBack" : " 31/3/15 09:57",
		"stepFileNameAtStep:" : " 31/3/15 09:57",
		"stepNameStart" : " 31/3/15 09:57",
		"storeBeforeManipulation" : " 31/3/15 09:57",
		"storeCurrentStep" : " 31/3/15 09:57",
		"terminateAllProcesses" : " 31/3/15 09:57",
		"traceSize" : " 31/3/15 09:57",
		"traceSize:" : " 31/3/15 09:57",
		"undo" : " 31/3/15 09:57",
		"undoList" : " 31/3/15 09:57",
		"undoList:" : " 31/3/15 09:57",
		"updateCormasInterface" : " 31/3/15 09:57" } }
